huaweicloudsdkidentitycenteroidc/__init__.py
huaweicloudsdkidentitycenteroidc/v1/__init__.py
huaweicloudsdkidentitycenteroidc/v1/identitycenteroidc_async_client.py
huaweicloudsdkidentitycenteroidc/v1/identitycenteroidc_client.py
huaweicloudsdkidentitycenteroidc/v1/identitycenteroidc_credentials.py
huaweicloudsdkidentitycenteroidc/v1/model/__init__.py
huaweicloudsdkidentitycenteroidc/v1/model/client_info_dto.py
huaweicloudsdkidentitycenteroidc/v1/model/create_token_req_body.py
huaweicloudsdkidentitycenteroidc/v1/model/create_token_request.py
huaweicloudsdkidentitycenteroidc/v1/model/create_token_response.py
huaweicloudsdkidentitycenteroidc/v1/model/register_client_req_body.py
huaweicloudsdkidentitycenteroidc/v1/model/register_client_request.py
huaweicloudsdkidentitycenteroidc/v1/model/register_client_response.py
huaweicloudsdkidentitycenteroidc/v1/model/start_device_authorization_req_body.py
huaweicloudsdkidentitycenteroidc/v1/model/start_device_authorization_request.py
huaweicloudsdkidentitycenteroidc/v1/model/start_device_authorization_response.py
huaweicloudsdkidentitycenteroidc/v1/model/token_info_dto.py
huaweicloudsdkidentitycenteroidc/v1/region/__init__.py
huaweicloudsdkidentitycenteroidc/v1/region/identitycenteroidc_region.py
huaweicloudsdkidentitycenteroidc-3.1.184.dist-info/METADATA
huaweicloudsdkidentitycenteroidc-3.1.184.dist-info/WHEEL
huaweicloudsdkidentitycenteroidc-3.1.184.dist-info/licenses/LICENSE
huaweicloudsdkidentitycenteroidc-3.1.184.dist-info/RECORD
